{
  "handle": "RomiLifshitz",
  "bio": "Quantum machine learning, quantum information theory, non-local games, quantum security | co-founder @ stealth | ex-@pasqal_quantum @QuantumIQC",
  "followers": 178,
  "technical_depth": {
    "score": 9,
    "evidence": "Published Master's thesis on Noise-Robust Self-Testing for non-local games (arxiv:2505.13537, supervised by Thomas Vidick); undergrad thesis Quantum Deep Dreaming for quantum circuit design (arxiv:2211.04343); posts demonstrating deep quantum information theory knowledge, e.g., entanglement detection in noisy systems, quantum error correction analyses."
  },
  "project_evidence": {
    "score": 2,
    "evidence": "GitHub profile https://github.com/rolifshitz exists with 5 repositories (likely private, no public repos, stars, or activity visible); co-founder of stealth quantum startup; ex-Pasqal quantum algorithms developer, but no open-source contributions or shipped products evident."
  },
  "mission_alignment": {
    "score": 6,
    "evidence": "Bio emphasizes quantum machine learning; posts excitement about AI reasoning (o1/o3 discovering quantum results used by Scott Aaronson), attends NeurIPS for networking; follows frontier AI but content primarily quantum-focused."
  },
  "exceptional_ability": {
    "score": 8,
    "evidence": "Novel contributions to quantum self-testing under noise (applicable to noisy hardware); worked at Pasqal on quantum hardware/applications; co-founder stealth startup; collaborations/visits at top quantum labs (Weizmann, IQC, etc.)."
  },
  "communication": {
    "score": 8,
    "evidence": "Clear, structured Twitter threads explaining complex quantum concepts (e.g., non-local games for entanglement detection, noise robustness benchmarks); accessible explanations with visuals and references; engaging style."
  },
  "final_score": 63.50000000000001,
  "summary": "Romi Lifshitz is a strong quantum information researcher with publications from Master's under Thomas Vidick and practical experience at Pasqal, showing depth in quantum-ML intersections. While enthusiastic about AI reasoning advances, lacks visible software engineering projects or core ML scaling work. Suitable for research roles bridging quantum and AI.",
  "strengths": [
    "Deep quantum research with publications",
    "Interest in AI reasoning and quantum ML",
    "Startup founding experience"
  ],
  "concerns": [
    "No public GitHub repos or OSS contributions",
    "Primary focus on quantum over classical ML/AGI",
    "Low X engagement and visibility"
  ],
  "recommended_role": "research",
  "github_url": "https://github.com/rolifshitz",
  "linkedin_url": null,
  "top_repos": [],
  "citations": [
    "https://x.com/i/status/1994945495870083318",
    "https://arxiv.org/abs/2505.13537",
    "https://arxiv.org/pdf/2211.04343",
    "https://x.com/i/status/1925202813207855110",
    "https://www.researchgate.net/publication/365209674_Quantum_Deep_Dreaming_A_Novel_Approach_for_Quantum_Circuit_Design",
    "https://x.com/i/status/1828899439798259868",
    "https://drops.dagstuhl.de/storage/00lipics/lipics-vol350-tqc2025/LIPIcs.TQC.2025.0/LIPIcs.TQC.2025.0.pdf",
    "https://www.arxiv.org/list/cs.IT/2025-05?skip=175&show=1000",
    "https://x.com/i/status/1838429750877962299",
    "https://x.com/i/status/1925202794635571342",
    "https://tilt.io/backchannel/profiles/romi-lifshitz",
    "https://www.semanticscholar.org/paper/Quantum-Neural-Networks%253A-Concepts%252C-Applications%252C-Kwak-Yun/9fdb6d6da1261dbfa2153e6cb007d6d71f25c628",
    "https://x.com/i/status/1980743204665454762",
    "https://x.com/i/status/1832158925975691396",
    "https://arxiv.org/html/2312.16765v2",
    "https://x.com/i/status/1925202807029686349",
    "https://x.com/i/status/1985612098865672701",
    "https://x.com/i/status/1993817241809506538",
    "https://x.com/i/status/1925202799639318809",
    "https://x.com/i/status/1995233875489145239",
    "https://x.com/i/status/1995572439280160895",
    "https://x.com/i/status/1995346281959653513",
    "https://x.com/i/status/1980674663354364031",
    "https://x.com/i/status/1994952224427082120",
    "https://www.linkedin.com/in/dana-hershkovitz-lazar-0856516",
    "https://x.com/i/status/1993709417804804125",
    "https://x.com/i/status/1995124664721449238",
    "https://x.com/i/status/1993824367407739188",
    "https://x.com/i/status/1925202803108065432",
    "https://arxiv.org/abs/2211.04343",
    "https://x.com/i/status/1925202820229165389",
    "https://www.youtube.com/watch?v=iU9HcNLC4Ak",
    "https://ml4physicalsciences.github.io/2023/files/NeurIPS_ML4PS_2023_55.pdf",
    "https://x.com/i/status/1994315530321174705",
    "https://x.com/i/status/1832515259367669823",
    "https://x.com/i/status/1828899449801978181",
    "https://x.com/i/status/1948500482177335428",
    "https://twitter.com/search?f=tweets&vertical=default&q=%2523Lifshitz",
    "https://x.com/i/status/1996148326249660564",
    "https://scholar.google.com/citations?user=z9fPNkAAAAAJ&hl=en",
    "https://x.com/i/status/1973071069016641829",
    "https://x.com/i/status/1995590992762994832",
    "https://x.com/i/status/1994594724569882748",
    "https://x.com/i/status/1948091283718942886",
    "https://x.com/i/status/1995243031650562169",
    "https://x.com/i/status/1985624447169261668",
    "https://x.com/i/status/1973123197651525684",
    "https://uwaterloo.ca/institute-for-quantum-computing/sites/default/files/uploads/documents/iqc-annual-report-to-ised-2023-2024-fin_removed.docx",
    "https://x.com/i/status/1995245022871228780",
    "https://x.com/i/status/1909283427159097527",
    "https://x.com/i/status/1829245179674669267",
    "https://www.semanticscholar.org/paper/fd7524b51c7b631dafe7c81332656225a496476a",
    "https://twitter.com/RomiLifshitz/highlights",
    "https://scispace.com/authors/romi-lifshitz-1068tb6s78",
    "https://x.com/i/status/1995647375583707496",
    "https://www.linkedin.com/in/tomermiara",
    "https://github.com/qosf/awesome-quantum-software",
    "https://x.com/RomiLifshitz/highlights",
    "https://x.com/i/status/1975639841665863857",
    "https://x.com/i/status/1993805015463678350",
    "https://x.com/i/status/1828899445280563477",
    "https://piclur.com/search/%2523NeurIPS",
    "https://x.com/i/status/1995244141840920639",
    "https://x.com/i/status/1925283329529520395",
    "https://uwaterloo.ca/institute-for-quantum-computing/sites/default/files/uploads/documents/rapport-annuel-de-liqc-a-isde-2023-2024_fin-removed.docx",
    "https://www.physik.fu-berlin.de/en/einrichtungen/ag/ag-eisert/team/visitors/index.html",
    "https://arxiv.org/html/2505.13537v1",
    "https://x.com/i/status/1995271109055480270",
    "https://github.com/orgs/Qiskit/repositories",
    "https://x.com/i/status/1832407658923749510",
    "https://x.com/i/status/1829245172070395921",
    "https://inspirehep.net/literature/2973223",
    "https://x.com/i/status/1925202810167042546",
    "https://x.com/i/status/1975632627202752938",
    "https://x.com/i/status/1829245175199141978",
    "http://arxiv.org/list/quant-ph/2022-11?skip=130&show=2000",
    "https://inspirehep.net/literature/2861471",
    "https://github.com/awesomelistsio/awesome-quantum-programming-frameworks",
    "https://www.researchgate.net/publication/385546938_A_Quantum_Computation_Language-based_Quantum_Compiler",
    "https://x.com/i/status/1874612648345817379",
    "https://x.com/i/status/1832622042316734654",
    "https://x.com/i/status/1832518162765771156",
    "https://x.com/i/status/1993061546424254907",
    "https://x.com/i/status/1994952142264918288",
    "https://x.com/i/status/1925341794448924686",
    "https://x.com/i/status/1995666955605606623",
    "https://github.com/desireevl/awesome-quantum-computing",
    "https://www6.twstalker.com/kunalsharmaq",
    "https://x.com/i/status/1995216367608647958",
    "https://x.com/i/status/1993480449088463068",
    "https://x.com/i/status/1973101040200221068",
    "https://www.linkedin.com/posts/shift-mobility_shiftmobility-futuremobility-sustainability-activity-6960990123874205696-lNTQ",
    "https://x.com/i/status/1838644740784353637",
    "https://www.linkedin.com/in/reut-cohen-zedek-70982372",
    "https://x.com/i/status/1994657877039149177",
    "https://x.com/RomiLifshitz",
    "https://github.com/rolifshitz",
    "https://x.com/i/status/1814739951499579590",
    "https://inspirehep.net/literature/2922986",
    "https://www.arxiv.org/list/cs/2025-05?skip=13775&show=100",
    "https://x.com/i/status/1925202816768815356",
    "https://github.com/rodyherrera/Quantum",
    "https://x.com/i/status/1829245178231525389",
    "https://rocketreach.co/romi-lifshitz-email_601849110",
    "https://www.urncst.com/index.php/urncst/article/download/118/20",
    "https://x.com/i/status/1980752763064639664",
    "https://schedule.sxsw.com/2023/contributors/2065841",
    "https://x.com/i/status/1829245173706174794",
    "https://x.com/i/status/1829245176755163487",
    "https://x.com/i/status/1994829160628588976",
    "https://github.com/JohnCoogan/learnquantum",
    "https://x.com/i/status/1909283969729785894",
    "https://x.com/i/status/1832120792429293899",
    "https://scispace.com/pdf/quantum-deep-dreaming-a-novel-approach-for-quantum-circuit-222r1boq.pdf",
    "https://github.com/quantum",
    "https://www.researchgate.net/figure/Convincingness-Behaviour-Analysis-for-Near-Infinite-Unequal-Resources-Between-CHSH-and_fig1_391912139",
    "https://news-dg.de/shift-mobility-im-september-2022-bei-der-ifa-berlin/",
    "https://x.com/i/status/1994553055514337406"
  ],
  "raw_response": "{\n  \"technical_depth\": {\"score\": 9, \"evidence\": \"Published Master's thesis on Noise-Robust Self-Testing for non-local games (arxiv:2505.13537, supervised by Thomas Vidick); undergrad thesis Quantum Deep Dreaming for quantum circuit design (arxiv:2211.04343); posts demonstrating deep quantum information theory knowledge, e.g., entanglement detection in noisy systems, quantum error correction analyses.\"},\n  \"project_evidence\": {\"score\": 2, \"evidence\": \"GitHub profile https://github.com/rolifshitz exists with 5 repositories (likely private, no public repos, stars, or activity visible); co-founder of stealth quantum startup; ex-Pasqal quantum algorithms developer, but no open-source contributions or shipped products evident.\"},\n  \"mission_alignment\": {\"score\": 6, \"evidence\": \"Bio emphasizes quantum machine learning; posts excitement about AI reasoning (o1/o3 discovering quantum results used by Scott Aaronson), attends NeurIPS for networking; follows frontier AI but content primarily quantum-focused.\"},\n  \"exceptional_ability\": {\"score\": 8, \"evidence\": \"Novel contributions to quantum self-testing under noise (applicable to noisy hardware); worked at Pasqal on quantum hardware/applications; co-founder stealth startup; collaborations/visits at top quantum labs (Weizmann, IQC, etc.).\"},\n  \"communication\": {\"score\": 8, \"evidence\": \"Clear, structured Twitter threads explaining complex quantum concepts (e.g., non-local games for entanglement detection, noise robustness benchmarks); accessible explanations with visuals and references; engaging style.\"},\n  \"summary\": \"Romi Lifshitz is a strong quantum information researcher with publications from Master's under Thomas Vidick and practical experience at Pasqal, showing depth in quantum-ML intersections. While enthusiastic about AI reasoning advances, lacks visible software engineering projects or core ML scaling work. Suitable for research roles bridging quantum and AI.\",\n  \"strengths\": [\"Deep quantum research with publications\", \"Interest in AI reasoning and quantum ML\", \"Startup founding experience\"],\n  \"concerns\": [\"No public GitHub repos or OSS contributions\", \"Primary focus on quantum over classical ML/AGI\", \"Low X engagement and visibility\"],\n  \"recommended_role\": \"research\",\n  \"github_url\": \"https://github.com/rolifshitz\",\n  \"linkedin_url\": null,\n  \"top_repos\": []\n}"
}